rfm_segmentation/__init__.py
rfm_segmentation/cli.py
rfm_segmentation/rfm_segmentation.py
rfm_segmentation-0.1.0.dist-info/AUTHORS.rst
rfm_segmentation-0.1.0.dist-info/LICENSE
rfm_segmentation-0.1.0.dist-info/METADATA
rfm_segmentation-0.1.0.dist-info/WHEEL
rfm_segmentation-0.1.0.dist-info/entry_points.txt
rfm_segmentation-0.1.0.dist-info/top_level.txt
rfm_segmentation-0.1.0.dist-info/RECORD
