Metadata-Version: 2.1
Name: rfm-segmentation
Version: 0.1.0
Summary: RFM Package for Customer Segmentation
Home-page: https://github.com/Esmila/rfm_segmentation
Author: Esmila Sahakyan
Author-email: esmila_sahakyan@edu.aua.am
License: MIT license
Keywords: rfm_segmentation
Platform: UNKNOWN
Classifier: Development Status :: 2 - Pre-Alpha
Classifier: Intended Audience :: Developers
Classifier: License :: OSI Approved :: MIT License
Classifier: Natural Language :: English
Classifier: Programming Language :: Python :: 3
Classifier: Programming Language :: Python :: 3.6
Classifier: Programming Language :: Python :: 3.7
Classifier: Programming Language :: Python :: 3.8
Requires-Python: >=3.6
Requires-Dist: Click (>=7.0)
